ialog/__init__.py
ialog/__main__.py
ialog/cli.py
ialog-0.2.1.dist-info/licenses/LICENSE
ialog-0.2.1.dist-info/METADATA
ialog-0.2.1.dist-info/WHEEL
ialog-0.2.1.dist-info/entry_points.txt
ialog-0.2.1.dist-info/top_level.txt
ialog-0.2.1.dist-info/RECORD
