Metadata-Version: 2.4
Name: ialog
Version: 0.2.1
Summary: AI-powered log analysis tool using Groq API
Home-page: https://github.com/yassir-aea/scanux
Author: Yassir AIT EL AIZZI
Author-email: Yassir Ait Elaizzi <yassir.aitelaizzi@gmail.com>
License: MIT
Project-URL: Homepage, https://github.com/yassir-aea/ialog
Project-URL: Documentation, https://github.com/yassir-aea/ialog#readme
Project-URL: Repository, https://github.com/yassir-aea/ialog.git
Classifier: Development Status :: 3 - Alpha
Classifier: Intended Audience :: System Administrators
Classifier: License :: OSI Approved :: MIT License
Classifier: Operating System :: POSIX :: Linux
Classifier: Programming Language :: Python :: 3
Classifier: Programming Language :: Python :: 3.8
Classifier: Programming Language :: Python :: 3.9
Classifier: Programming Language :: Python :: 3.10
Classifier: Programming Language :: Python :: 3.11
Classifier: Topic :: System :: Systems Administration
Classifier: Topic :: Security
Requires-Python: >=3.6
License-File: LICENSE
Requires-Dist: requests>=2.31.0
Requires-Dist: rich>=13.7.0
Requires-Dist: click>=8.1.7
Requires-Dist: python-dotenv>=1.0.0
Requires-Dist: pyyaml>=6.0.1
Dynamic: author
Dynamic: home-page
Dynamic: license-file
Dynamic: requires-python
